setup.py
brukva/__init__.py
brukva/adisp.py
brukva/client.py
brukva/exceptions.py
brukva.egg-info/PKG-INFO
brukva.egg-info/SOURCES.txt
brukva.egg-info/dependency_links.txt
brukva.egg-info/top_level.txt