Metadata-Version: 1.0
Name: brukva
Version: 0.0.1
Summary: Asynchronous Redis client that works within the Tornado IO loop
Home-page: http://github.com/kmerenkov/brukva
Author: Konstantin Merenkov
Author-email: kmerenkov@gmail.com
License: WTFPL
Keywords: Redis,Tornado
Platform: UNKNOWN
